{
  "1": [
    {
      "nameEn": "Nature Neuroscience",
      "nameCn": "自然神经科学",
      "abbr": "NAT NEUROSCI",
      "issn": "1097-6256",
      "impactFactor": 24.884,
      "hIndex": 401,
      "citeScore": 26.9,
      "jcrQuartile": "Q1",
      "casCategory": "医学",
      "casSubcategory": "神经科学",
      "indexing": "SCI",
      "isOA": "No",
      "discipline": "neuroscience"
    },
    {
      "nameEn": "Neuron",
      "nameCn": "神经元",
      "abbr": "NEURON",
      "issn": "0896-6273",
      "impactFactor": 18.882,
      "hIndex": 479,
      "citeScore": 19.5,
      "jcrQuartile": "Q1",
      "casCategory": "医学",
      "casSubcategory": "神经科学",
      "indexing": "SCI",
      "isOA": "No",
      "discipline": "neuroscience"
    },
    {
      "nameEn": "Molecular Psychiatry",
      "nameCn": "分子精神病学",
      "abbr": "MOL PSYCHIATR",
      "issn": "1359-4184",
      "impactFactor": 15.992,
      "hIndex": 213,
      "citeScore": 17.3,
      "jcrQuartile": "Q1",
      "casCategory": "医学",
      "casSubcategory": "精神病学",
      "indexing": "SCI",
      "isOA": "No",
      "discipline": "psychiatry"
    },
    {
      "nameEn": "Biological Psychiatry",
      "nameCn": "生物精神病学",
      "abbr": "BIOL PSYCHIAT",
      "issn": "0006-3223",
      "impactFactor": 13.382,
      "hIndex": 290,
      "citeScore": 18.8,
      "jcrQuartile": "Q1",
      "casCategory": "医学",
      "casSubcategory": "精神病学",
      "indexing": "SCIE",
      "isOA": "No",
      "discipline": "psychiatry"
    },
    {
      "nameEn": "JAMA Psychiatry",
      "nameCn": "美国医学会精神病学",
      "abbr": "JAMA PSYCHIATRY",
      "issn": "2168-622X",
      "impactFactor": 21.596,
      "hIndex": 172,
      "citeScore": 23.4,
      "jcrQuartile": "Q1",
      "casCategory": "医学",
      "casSubcategory": "精神病学",
      "indexing": "SCI",
      "isOA": "No",
      "discipline": "psychiatry"
    },
    {
      "nameEn": "Brain",
      "nameCn": "脑",
      "abbr": "BRAIN",
      "issn": "0006-8950",
      "impactFactor": 13.501,
      "hIndex": 313,
      "citeScore": 15.9,
      "jcrQuartile": "Q1",
      "casCategory": "医学",
      "casSubcategory": "神经科学",
      "indexing": "SCI",
      "isOA": "No",
      "discipline": "neuroscience"
    },
    {
      "nameEn": "Annals of Neurology",
      "nameCn": "神经病学年鉴",
      "abbr": "ANN NEUROL",
      "issn": "0364-5134",
      "impactFactor": 10.422,
      "hIndex": 246,
      "citeScore": 13.1,
      "jcrQuartile": "Q1",
      "casCategory": "医学",
      "casSubcategory": "神经病学",
      "indexing": "SCI",
      "isOA": "No",
      "discipline": "neurology"
    },
    {
      "nameEn": "World Psychiatry",
      "nameCn": "世界精神病学",
      "abbr": "WORLD PSYCHIATRY",
      "issn": "1723-8617",
      "impactFactor": 79.683,
      "hIndex": 121,
      "citeScore": 65.3,
      "jcrQuartile": "Q1",
      "casCategory": "医学",
      "casSubcategory": "精神病学",
      "indexing": "SCI",
      "isOA": "Yes",
      "discipline": "psychiatry"
    },
    {
      "nameEn": "The Lancet Psychiatry",
      "nameCn": "柳叶刀精神病学",
      "abbr": "LANCET PSYCHIATRY",
      "issn": "2215-0366",
      "impactFactor": 27.083,
      "hIndex": 112,
      "citeScore": 24.7,
      "jcrQuartile": "Q1",
      "casCategory": "医学",
      "casSubcategory": "精神病学",
      "indexing": "SCI",
      "isOA": "No",
      "discipline": "psychiatry"
    },
    {
      "nameEn": "Trends in Neurosciences",
      "nameCn": "神经科学趋势",
      "abbr": "TRENDS NEUROSCI",
      "issn": "0166-2236",
      "impactFactor": 17.755,
      "hIndex": 275,
      "citeScore": 17.2,
      "jcrQuartile": "Q1",
      "casCategory": "医学",
      "casSubcategory": "神经科学",
      "indexing": "SCI",
      "isOA": "No",
      "discipline": "neuroscience"
    },
    {
      "nameEn": "Nature Reviews Neuroscience",
      "nameCn": "自然评论：神经科学",
      "abbr": "NAT REV NEUROSCI",
      "issn": "1471-003X",
      "impactFactor": 38.786,
      "hIndex": 410,
      "citeScore": 40.1,
      "jcrQuartile": "Q1",
      "casCategory": "医学",
      "casSubcategory": "神经科学",
      "indexing": "SCI",
      "isOA": "No",
      "discipline": "neuroscience"
    },
    {
      "nameEn": "Cell Stem Cell",
      "nameCn": "细胞干细胞",
      "abbr": "CELL STEM CELL",
      "issn": "1934-5909",
      "impactFactor": 25.269,
      "hIndex": 264,
      "citeScore": 27.8,
      "jcrQuartile": "Q1",
      "casCategory": "生物学",
      "casSubcategory": "细胞生物学",
      "indexing": "SCI",
      "isOA": "No",
      "discipline": "related"
    },
    {
      "nameEn": "The Lancet Neurology",
      "nameCn": "柳叶刀神经病学",
      "abbr": "LANCET NEUROL",
      "issn": "1474-4422",
      "impactFactor": 44.184,
      "hIndex": 278,
      "citeScore": 38.2,
      "jcrQuartile": "Q1",
      "casCategory": "医学",
      "casSubcategory": "神经病学",
      "indexing": "SCI",
      "isOA": "No",
      "discipline": "neurology"
    },
    {
      "nameEn": "Nature Human Behaviour",
      "nameCn": "自然人类行为",
      "abbr": "NAT HUM BEHAV",
      "issn": "2397-3374",
      "impactFactor": 15.53,
      "hIndex": 98,
      "citeScore": 18.1,
      "jcrQuartile": "Q1",
      "casCategory": "心理学",
      "casSubcategory": "心理学",
      "indexing": "SSCI",
      "isOA": "No",
      "discipline": "related"
    },
    {
      "nameEn": "American Journal of Psychiatry",
      "nameCn": "美国精神病学杂志",
      "abbr": "AM J PSYCHIAT",
      "issn": "0002-953X",
      "impactFactor": 18.112,
      "hIndex": 305,
      "citeScore": 19.8,
      "jcrQuartile": "Q1",
      "casCategory": "医学",
      "casSubcategory": "精神病学",
      "indexing": "SCI",
      "isOA": "No",
      "discipline": "psychiatry"
    },
    {
      "nameEn": "Annual Review of Neuroscience",
      "nameCn": "神经科学年度评论",
      "abbr": "ANNU REV NEUROSCI",
      "issn": "0147-006X",
      "impactFactor": 16.92,
      "hIndex": 220,
      "citeScore": 18.5,
      "jcrQuartile": "Q1",
      "casCategory": "医学",
      "casSubcategory": "神经科学",
      "indexing": "SCI",
      "isOA": "No",
      "discipline": "neuroscience"
    }
  ],
  "2": [
    {
      "nameEn": "Journal of Neuroscience",
      "nameCn": "神经科学杂志",
      "abbr": "J NEUROSCI",
      "issn": "0270-6474",
      "impactFactor": 6.673,
      "hIndex": 409,
      "citeScore": 9.1,
      "jcrQuartile": "Q1",
      "casCategory": "医学",
      "casSubcategory": "神经科学",
      "indexing": "SCI",
      "isOA": "No",
      "discipline": "neuroscience"
    },
    {
      "nameEn": "Neuropsychopharmacology",
      "nameCn": "神经精神药理学",
      "abbr": "NEUROPSYCHOPHARMACOL",
      "issn": "0893-133X",
      "impactFactor": 8.294,
      "hIndex": 235,
      "citeScore": 10.8,
      "jcrQuartile": "Q1",
      "casCategory": "医学",
      "casSubcategory": "精神病学",
      "indexing": "SCI",
      "isOA": "No",
      "discipline": "psychiatry"
    },
    {
      "nameEn": "European Neuropsychopharmacology",
      "nameCn": "欧洲神经精神药理学",
      "abbr": "EUR NEUROPSYCHOPHARM",
      "issn": "0924-977X",
      "impactFactor": 6.292,
      "hIndex": 139,
      "citeScore": 6.7,
      "jcrQuartile": "Q1",
      "casCategory": "医学",
      "casSubcategory": "精神病学",
      "indexing": "SCI",
      "isOA": "No",
      "discipline": "psychiatry"
    },
    {
      "nameEn": "Brain Stimulation",
      "nameCn": "大脑刺激",
      "abbr": "BRAIN STIMUL",
      "issn": "1935-861X",
      "impactFactor": 8.955,
      "hIndex": 115,
      "citeScore": 12.7,
      "jcrQuartile": "Q1",
      "casCategory": "医学",
      "casSubcategory": "神经科学",
      "indexing": "SCI",
      "isOA": "No",
      "discipline": "neuroscience"
    },
    {
      "nameEn": "Neurology",
      "nameCn": "神经病学",
      "abbr": "NEUROLOGY",
      "issn": "0028-3878",
      "impactFactor": 9.91,
      "hIndex": 335,
      "citeScore": 11.6,
      "jcrQuartile": "Q1",
      "casCategory": "医学",
      "casSubcategory": "神经病学",
      "indexing": "SCI",
      "isOA": "No",
      "discipline": "neurology"
    },
    {
      "nameEn": "Brain Pathology",
      "nameCn": "脑病理学",
      "abbr": "BRAIN PATHOL",
      "issn": "1015-6305",
      "impactFactor": 7.528,
      "hIndex": 118,
      "citeScore": 8.3,
      "jcrQuartile": "Q1",
      "casCategory": "医学",
      "casSubcategory": "神经科学",
      "indexing": "SCI",
      "isOA": "No",
      "discipline": "neuroscience"
    },
    {
      "nameEn": "Journal of Psychiatric Research",
      "nameCn": "精神病学研究杂志",
      "abbr": "J PSYCHIATR RES",
      "issn": "0022-3956",
      "impactFactor": 5.168,
      "hIndex": 146,
      "citeScore": 7.3,
      "jcrQuartile": "Q1",
      "casCategory": "医学",
      "casSubcategory": "精神病学",
      "indexing": "SCI",
      "isOA": "No",
      "discipline": "psychiatry"
    },
    {
      "nameEn": "Schizophrenia Bulletin",
      "nameCn": "精神分裂症公报",
      "abbr": "SCHIZOPHR BULL",
      "issn": "0586-7614",
      "impactFactor": 9.306,
      "hIndex": 211,
      "citeScore": 11.5,
      "jcrQuartile": "Q1",
      "casCategory": "医学",
      "casSubcategory": "精神病学",
      "indexing": "SCI",
      "isOA": "No",
      "discipline": "psychiatry"
    },
    {
      "nameEn": "Cortex",
      "nameCn": "大脑皮层",
      "abbr": "CORTEX",
      "issn": "0010-9452",
      "impactFactor": 5.217,
      "hIndex": 148,
      "citeScore": 6.5,
      "jcrQuartile": "Q1",
      "casCategory": "医学",
      "casSubcategory": "神经科学",
      "indexing": "SCI",
      "isOA": "No",
      "discipline": "neuroscience"
    },
    {
      "nameEn": "Developmental Cognitive Neuroscience",
      "nameCn": "发育认知神经科学",
      "abbr": "DEV COGN NEUROSCI",
      "issn": "1878-9293",
      "impactFactor": 6.104,
      "hIndex": 95,
      "citeScore": 8.9,
      "jcrQuartile": "Q1",
      "casCategory": "医学",
      "casSubcategory": "神经科学",
      "indexing": "SCI",
      "isOA": "Yes",
      "discipline": "neuroscience"
    },
    {
      "nameEn": "Neurobiology of Disease",
      "nameCn": "疾病神经生物学",
      "abbr": "NEUROBIOL DIS",
      "issn": "0969-9961",
      "impactFactor": 6.629,
      "hIndex": 188,
      "citeScore": 8.7,
      "jcrQuartile": "Q1",
      "casCategory": "医学",
      "casSubcategory": "神经科学",
      "indexing": "SCI",
      "isOA": "No",
      "discipline": "neuroscience"
    },
    {
      "nameEn": "Journal of Child Psychology and Psychiatry",
      "nameCn": "儿童心理学与精神病学杂志",
      "abbr": "J CHILD PSYCHOL PSYC",
      "issn": "0021-9630",
      "impactFactor": 8.982,
      "hIndex": 216,
      "citeScore": 10.5,
      "jcrQuartile": "Q1",
      "casCategory": "心理学",
      "casSubcategory": "发育心理学",
      "indexing": "SSCI",
      "isOA": "No",
      "discipline": "related"
    },
    {
      "nameEn": "Movement Disorders",
      "nameCn": "运动障碍",
      "abbr": "MOV DISORD",
      "issn": "0885-3185",
      "impactFactor": 8.679,
      "hIndex": 201,
      "citeScore": 9.9,
      "jcrQuartile": "Q1",
      "casCategory": "医学",
      "casSubcategory": "神经病学",
      "indexing": "SCI",
      "isOA": "No",
      "discipline": "neurology"
    },
    {
      "nameEn": "NeuroImage",
      "nameCn": "神经影像",
      "abbr": "NEUROIMAGE",
      "issn": "1053-8119",
      "impactFactor": 6.556,
      "hIndex": 333,
      "citeScore": 9.2,
      "jcrQuartile": "Q1",
      "casCategory": "工程技术",
      "casSubcategory": "工程：生物医学",
      "indexing": "SCI",
      "isOA": "No",
      "discipline": "related"
    },
    {
      "nameEn": "Journal of Neurology, Neurosurgery & Psychiatry",
      "nameCn": "神经病学、神经外科学与精神病学杂志",
      "abbr": "J NEUROL NEUROSUR PS",
      "issn": "0022-3050",
      "impactFactor": 8.256,
      "hIndex": 215,
      "citeScore": 10.1,
      "jcrQuartile": "Q1",
      "casCategory": "医学",
      "casSubcategory": "神经病学",
      "indexing": "SCI",
      "isOA": "No",
      "discipline": "neurology"
    },
    {
      "nameEn": "Biological Psychiatry: Cognitive Neuroscience and Neuroimaging",
      "nameCn": "生物精神病学：认知神经科学与神经影像",
      "abbr": "BIOL PSYCHIAT CN...",
      "issn": "2451-9022",
      "impactFactor": 6.161,
      "hIndex": 55,
      "citeScore": 8.5,
      "jcrQuartile": "Q1",
      "casCategory": "医学",
      "casSubcategory": "精神病学",
      "indexing": "SCIE",
      "isOA": "No",
      "discipline": "psychiatry"
    }
  ],
  "3": [
    {
      "nameEn": "ACS Chemical Neuroscience",
      "nameCn": "ACS化学神经科学",
      "abbr": "ACS CHEM NEUROSCI",
      "issn": "1948-7193",
      "impactFactor": 4.418,
      "hIndex": 87,
      "citeScore": 6.8,
      "jcrQuartile": "Q2",
      "casCategory": "医学",
      "casSubcategory": "神经科学",
      "indexing": "SCIE",
      "isOA": "No",
      "discipline": "neuroscience"
    },
    {
      "nameEn": "International Journal of Neuropsychopharmacology",
      "nameCn": "国际神经精神药理学杂志",
      "abbr": "INT J NEUROPSYCHOPH",
      "issn": "1461-1457",
      "impactFactor": 4.207,
      "hIndex": 102,
      "citeScore": 5.7,
      "jcrQuartile": "Q2",
      "casCategory": "医学",
      "casSubcategory": "精神病学",
      "indexing": "SCI",
      "isOA": "Yes",
      "discipline": "psychiatry"
    },
    {
      "nameEn": "Neuropsychology Review",
      "nameCn": "神经心理学评论",
      "abbr": "NEUROPSYCHOL REV",
      "issn": "1040-7308",
      "impactFactor": 5.358,
      "hIndex": 100,
      "citeScore": 7.6,
      "jcrQuartile": "Q2",
      "casCategory": "医学",
      "casSubcategory": "神经科学",
      "indexing": "SSCI",
      "isOA": "No",
      "discipline": "neuroscience"
    },
    {
      "nameEn": "Journal of Attention Disorders",
      "nameCn": "注意力障碍杂志",
      "abbr": "J ATTEN DISORD",
      "issn": "1087-0547",
      "impactFactor": 4.365,
      "hIndex": 94,
      "citeScore": 6.1,
      "jcrQuartile": "Q2",
      "casCategory": "医学",
      "casSubcategory": "精神病学",
      "indexing": "SSCI",
      "isOA": "No",
      "discipline": "psychiatry"
    },
    {
      "nameEn": "Journal of Neuropsychiatry and Clinical Neurosciences",
      "nameCn": "神经精神病学与临床神经科学杂志",
      "abbr": "J NEUROPSYCH CLIN N",
      "issn": "0895-0172",
      "impactFactor": 3.704,
      "hIndex": 89,
      "citeScore": 4.1,
      "jcrQuartile": "Q2",
      "casCategory": "医学",
      "casSubcategory": "神经病学",
      "indexing": "SCI",
      "isOA": "No",
      "discipline": "neurology"
    },
    {
      "nameEn": "CNS Neuroscience & Therapeutics",
      "nameCn": "中枢神经系统神经科学与治疗",
      "abbr": "CNS NEUROSCI THER",
      "issn": "1755-5930",
      "impactFactor": 4.107,
      "hIndex": 62,
      "citeScore": 5.8,
      "jcrQuartile": "Q2",
      "casCategory": "医学",
      "casSubcategory": "神经科学",
      "indexing": "SCI",
      "isOA": "Yes",
      "discipline": "neuroscience"
    },
    {
      "nameEn": "Psychiatry Research",
      "nameCn": "精神病学研究",
      "abbr": "PSYCHIAT RES",
      "issn": "0165-1781",
      "impactFactor": 3.222,
      "hIndex": 144,
      "citeScore": 3.9,
      "jcrQuartile": "Q2",
      "casCategory": "医学",
      "casSubcategory": "精神病学",
      "indexing": "SCI",
      "isOA": "No",
      "discipline": "psychiatry"
    },
    {
      "nameEn": "Journal of Neurology",
      "nameCn": "神经病学杂志",
      "abbr": "J NEUROL",
      "issn": "0340-5354",
      "impactFactor": 4.849,
      "hIndex": 154,
      "citeScore": 5.1,
      "jcrQuartile": "Q1",
      "casCategory": "医学",
      "casSubcategory": "神经病学",
      "indexing": "SCI",
      "isOA": "No",
      "discipline": "neurology"
    },
    {
      "nameEn": "Journal of Neurodevelopmental Disorders",
      "nameCn": "神经发育障碍杂志",
      "abbr": "J NEURODEV DISORD",
      "issn": "1866-1947",
      "impactFactor": 3.785,
      "hIndex": 55,
      "citeScore": 5.3,
      "jcrQuartile": "Q2",
      "casCategory": "医学",
      "casSubcategory": "神经科学",
      "indexing": "SCI",
      "isOA": "Yes",
      "discipline": "neuroscience"
    },
    {
      "nameEn": "Molecular Autism",
      "nameCn": "分子自闭症",
      "abbr": "MOL AUTISM",
      "issn": "2040-2392",
      "impactFactor": 5.712,
      "hIndex": 71,
      "citeScore": 7.9,
      "jcrQuartile": "Q1",
      "casCategory": "医学",
      "casSubcategory": "精神病学",
      "indexing": "SCI",
      "isOA": "Yes",
      "discipline": "psychiatry"
    },
    {
      "nameEn": "NeuroImage: Clinical",
      "nameCn": "神经影像：临床",
      "abbr": "NEUROIMAGE-CLIN",
      "issn": "2213-1582",
      "impactFactor": 4.881,
      "hIndex": 86,
      "citeScore": 7.2,
      "jcrQuartile": "Q1",
      "casCategory": "医学",
      "casSubcategory": "神经影像学",
      "indexing": "SCIE",
      "isOA": "Yes",
      "discipline": "related"
    },
    {
      "nameEn": "Journal of Affective Disorders",
      "nameCn": "情感障碍杂志",
      "abbr": "J AFFECT DISORDERS",
      "issn": "0165-0327",
      "impactFactor": 4.839,
      "hIndex": 173,
      "citeScore": 6.5,
      "jcrQuartile": "Q1",
      "casCategory": "医学",
      "casSubcategory": "精神病学",
      "indexing": "SCI",
      "isOA": "No",
      "discipline": "psychiatry"
    },
    {
      "nameEn": "European Journal of Neurology",
      "nameCn": "欧洲神经病学杂志",
      "abbr": "EUR J NEUROL",
      "issn": "1351-5101",
      "impactFactor": 4.494,
      "hIndex": 127,
      "citeScore": 5.9,
      "jcrQuartile": "Q2",
      "casCategory": "医学",
      "casSubcategory": "神经病学",
      "indexing": "SCI",
      "isOA": "No",
      "discipline": "neurology"
    },
    {
      "nameEn": "Journal of Neuroinflammation",
      "nameCn": "神经炎症杂志",
      "abbr": "J NEUROINFLAMM",
      "issn": "1742-2094",
      "impactFactor": 5.793,
      "hIndex": 122,
      "citeScore": 8.1,
      "jcrQuartile": "Q1",
      "casCategory": "医学",
      "casSubcategory": "神经科学",
      "indexing": "SCI",
      "isOA": "Yes",
      "discipline": "neuroscience"
    },
    {
      "nameEn": "Schizophrenia Research",
      "nameCn": "精神分裂症研究",
      "abbr": "SCHIZOPHR RES",
      "issn": "0920-9964",
      "impactFactor": 4.66,
      "hIndex": 172,
      "citeScore": 6.3,
      "jcrQuartile": "Q1",
      "casCategory": "医学",
      "casSubcategory": "精神病学",
      "indexing": "SCI",
      "isOA": "No",
      "discipline": "psychiatry"
    },
    {
      "nameEn": "Journal of Alzheimer's Disease",
      "nameCn": "阿尔茨海默病杂志",
      "abbr": "J ALZHEIMERS DIS",
      "issn": "1387-2877",
      "impactFactor": 4.472,
      "hIndex": 149,
      "citeScore": 6.1,
      "jcrQuartile": "Q2",
      "casCategory": "医学",
      "casSubcategory": "神经病学",
      "indexing": "SCI",
      "isOA": "No",
      "discipline": "neurology"
    },
    {
      "nameEn": "Social Cognitive and Affective Neuroscience",
      "nameCn": "社会认知与情感神经科学",
      "abbr": "SOC COGN AFFECT NEUR",
      "issn": "1749-5016",
      "impactFactor": 3.615,
      "hIndex": 97,
      "citeScore": 5.8,
      "jcrQuartile": "Q2",
      "casCategory": "心理学",
      "casSubcategory": "心理学：实验",
      "indexing": "SSCI",
      "isOA": "Yes",
      "discipline": "related"
    }
  ],
  "4": [
    {
      "nameEn": "Neuroscience Letters",
      "nameCn": "神经科学快报",
      "abbr": "NEUROSCI LETT",
      "issn": "0304-3940",
      "impactFactor": 3.046,
      "hIndex": 155,
      "citeScore": 3.5,
      "jcrQuartile": "Q3",
      "casCategory": "医学",
      "casSubcategory": "神经科学",
      "indexing": "SCIE",
      "isOA": "No",
      "discipline": "neuroscience"
    },
    {
      "nameEn": "Neuropsychiatric Disease and Treatment",
      "nameCn": "神经精神疾病及治疗",
      "abbr": "NEUROPSYCH DIS TREAT",
      "issn": "1176-6328",
      "impactFactor": 2.808,
      "hIndex": 78,
      "citeScore": 3.4,
      "jcrQuartile": "Q3",
      "casCategory": "医学",
      "casSubcategory": "精神病学",
      "indexing": "SCIE",
      "isOA": "Yes",
      "discipline": "psychiatry"
    },
    {
      "nameEn": "Neurological Sciences",
      "nameCn": "神经学科学",
      "abbr": "NEUROL SCI",
      "issn": "1590-1874",
      "impactFactor": 3.307,
      "hIndex": 84,
      "citeScore": 3.8,
      "jcrQuartile": "Q3",
      "casCategory": "医学",
      "casSubcategory": "神经病学",
      "indexing": "SCI",
      "isOA": "No",
      "discipline": "neurology"
    },
    {
      "nameEn": "General Psychiatry",
      "nameCn": "普通精神病学",
      "abbr": "GEN PSYCHIATR",
      "issn": "2517-729X",
      "impactFactor": 3.242,
      "hIndex": 26,
      "citeScore": 4.2,
      "jcrQuartile": "Q3",
      "casCategory": "医学",
      "casSubcategory": "精神病学",
      "indexing": "SCIE",
      "isOA": "Yes",
      "discipline": "psychiatry"
    },
    {
      "nameEn": "Neuropsychiatry",
      "nameCn": "神经精神病学",
      "abbr": "NEUROPSYCHIATRY-UK",
      "issn": "1758-2008",
      "impactFactor": 2.154,
      "hIndex": 34,
      "citeScore": 2.7,
      "jcrQuartile": "Q3",
      "casCategory": "医学",
      "casSubcategory": "精神病学",
      "indexing": "ESCI",
      "isOA": "No",
      "discipline": "psychiatry"
    },
    {
      "nameEn": "Neurology International",
      "nameCn": "国际神经病学",
      "abbr": "NEUROL INT",
      "issn": "2035-8377",
      "impactFactor": 2.012,
      "hIndex": 21,
      "citeScore": 2.3,
      "jcrQuartile": "Q4",
      "casCategory": "医学",
      "casSubcategory": "神经病学",
      "indexing": "ESCI",
      "isOA": "Yes",
      "discipline": "neurology"
    },
    {
      "nameEn": "Frontiers in Behavioral Neuroscience",
      "nameCn": "行为神经科学前沿",
      "abbr": "FRONT BEHAV NEUROSCI",
      "issn": "1662-5153",
      "impactFactor": 3.099,
      "hIndex": 97,
      "citeScore": 4.7,
      "jcrQuartile": "Q3",
      "casCategory": "医学",
      "casSubcategory": "神经科学",
      "indexing": "SCIE",
      "isOA": "Yes",
      "discipline": "neuroscience"
    },
    {
      "nameEn": "Behavioural Neurology",
      "nameCn": "行为神经病学",
      "abbr": "BEHAV NEUROL",
      "issn": "0953-4180",
      "impactFactor": 2.521,
      "hIndex": 52,
      "citeScore": 2.9,
      "jcrQuartile": "Q3",
      "casCategory": "医学",
      "casSubcategory": "神经科学",
      "indexing": "SCIE",
      "isOA": "Yes",
      "discipline": "neuroscience"
    },
    {
      "nameEn": "Asian Journal of Psychiatry",
      "nameCn": "亚洲精神病学杂志",
      "abbr": "ASIAN J PSYCHIATR",
      "issn": "1876-2018",
      "impactFactor": 3.129,
      "hIndex": 52,
      "citeScore": 3.6,
      "jcrQuartile": "Q3",
      "casCategory": "医学",
      "casSubcategory": "精神病学",
      "indexing": "SCIE",
      "isOA": "No",
      "discipline": "psychiatry"
    },
    {
      "nameEn": "Australasian Psychiatry",
      "nameCn": "澳大拉西亚精神病学",
      "abbr": "AUSTRALAS PSYCHIATRY",
      "issn": "1039-8562",
      "impactFactor": 1.233,
      "hIndex": 44,
      "citeScore": 1.6,
      "jcrQuartile": "Q4",
      "casCategory": "医学",
      "casSubcategory": "精神病学",
      "indexing": "SSCI",
      "isOA": "No",
      "discipline": "psychiatry"
    },
    {
      "nameEn": "Journal of Clinical Neuroscience",
      "nameCn": "临床神经科学杂志",
      "abbr": "J CLIN NEUROSCI",
      "issn": "0967-5868",
      "impactFactor": 2.065,
      "hIndex": 80,
      "citeScore": 2.5,
      "jcrQuartile": "Q4",
      "casCategory": "医学",
      "casSubcategory": "神经科学",
      "indexing": "SCIE",
      "isOA": "No",
      "discipline": "neuroscience"
    },
    {
      "nameEn": "BMC Psychiatry",
      "nameCn": "BMC精神病学",
      "abbr": "BMC PSYCHIATRY",
      "issn": "1471-244X",
      "impactFactor": 3.63,
      "hIndex": 104,
      "citeScore": 4.5,
      "jcrQuartile": "Q2",
      "casCategory": "医学",
      "casSubcategory": "精神病学",
      "indexing": "SCIE",
      "isOA": "Yes",
      "discipline": "psychiatry"
    },
    {
      "nameEn": "Clinical Neurology and Neurosurgery",
      "nameCn": "临床神经病学与神经外科学",
      "abbr": "CLIN NEUROL NEUROSUR",
      "issn": "0303-8467",
      "impactFactor": 2.287,
      "hIndex": 79,
      "citeScore": 2.8,
      "jcrQuartile": "Q3",
      "casCategory": "医学",
      "casSubcategory": "神经病学",
      "indexing": "SCIE",
      "isOA": "No",
      "discipline": "neurology"
    },
    {
      "nameEn": "Journal of Psychiatric Practice",
      "nameCn": "精神科实践杂志",
      "abbr": "J PSYCHIATR PRACT",
      "issn": "1527-4160",
      "impactFactor": 1.897,
      "hIndex": 50,
      "citeScore": 2.2,
      "jcrQuartile": "Q4",
      "casCategory": "医学",
      "casSubcategory": "精神病学",
      "indexing": "SCIE",
      "isOA": "No",
      "discipline": "psychiatry"
    },
    {
      "nameEn": "Current Opinion in Neurology",
      "nameCn": "神经病学最新观点",
      "abbr": "CURR OPIN NEUROL",
      "issn": "1350-7540",
      "impactFactor": 5.44,
      "hIndex": 144,
      "citeScore": 5.6,
      "jcrQuartile": "Q1",
      "casCategory": "医学",
      "casSubcategory": "神经病学",
      "indexing": "SCI",
      "isOA": "No",
      "discipline": "neurology"
    },
    {
      "nameEn": "Journal of Neurochemistry",
      "nameCn": "神经化学杂志",
      "abbr": "J NEUROCHEM",
      "issn": "0022-3042",
      "impactFactor": 4.082,
      "hIndex": 218,
      "citeScore": 5.9,
      "jcrQuartile": "Q2",
      "casCategory": "医学",
      "casSubcategory": "神经科学",
      "indexing": "SCI",
      "isOA": "No",
      "discipline": "neuroscience"
    },
    {
      "nameEn": "Psychiatry and Clinical Neurosciences",
      "nameCn": "精神病学与临床神经科学",
      "abbr": "PSYCHIAT CLIN NEUROS",
      "issn": "1323-1316",
      "impactFactor": 3.558,
      "hIndex": 87,
      "citeScore": 4.9,
      "jcrQuartile": "Q2",
      "casCategory": "医学",
      "casSubcategory": "精神病学",
      "indexing": "SCI",
      "isOA": "No",
      "discipline": "psychiatry"
    }
  ]
}
